addr2line/__init__.py
addr2line/base.py
addr2line-0.0.4.data/data/README.md/README.md
addr2line-0.0.4.dist-info/LICENSE
addr2line-0.0.4.dist-info/METADATA
addr2line-0.0.4.dist-info/WHEEL
addr2line-0.0.4.dist-info/top_level.txt
addr2line-0.0.4.dist-info/RECORD
