Metadata-Version: 2.1
Name: addr2line
Version: 0.0.4
Summary: interact with addr2line command
Home-page: https://github.com/ramwin/addr2line
Author: Xiang Wang
Author-email: ramwin@qq.com
License: MIT
Keywords: addr2line
Platform: UNKNOWN
Classifier: License :: OSI Approved :: MIT License
Classifier: Programming Language :: Python :: 3
License-File: LICENSE
Provides-Extra: dev
Provides-Extra: test
